snAPI/Constants.py
snAPI/HH500Lib.dll
snAPI/Main.py
snAPI/PH330Lib.dll
snAPI/Utils.py
snAPI/__init__.py
snAPI/hhlib64.dll
snAPI/libhh500lib.so
snAPI/libhhlib.so
snAPI/libmhlib.so
snAPI/libph330.so
snAPI/libsnAPI4Linux.so
snAPI/libth260lib.so
snAPI/mhlib64.dll
snAPI/snAPI64.dll
snAPI/system.ini
snAPI/system_linux.ini
snAPI/th260lib64.dll
snapi.libs/libblkid-a9167753.so.1.1.0
snapi.libs/libmount-ec61bd71.so.1.1.0
snapi.libs/libpcre2-8-516f4c9d.so.0.7.1
snapi.libs/libselinux-d0805dcb.so.1
snapi.libs/libudev-9765ffbd.so.1.6.11
snapi.libs/libusb-1-1b307d35.0.so.0.2.0
snapi.libs/libuuid-95b83d40.so.1.3.0
snapi-1.1.2.dist-info/METADATA
snapi-1.1.2.dist-info/WHEEL
snapi-1.1.2.dist-info/top_level.txt
snapi-1.1.2.dist-info/RECORD
snapi-1.1.2.dist-info/licenses/LICENSE.txt
