Metadata-Version: 2.4
Name: snapi
Version: 1.1.2
Summary: Python wrapper for PicoQuant's snAPI
Author-email: PicoQuant <support@picoquant.com>
License: Disclaimer
Requires: setuptools
Requires: wheel
Requires-Python: >=3.6
License-File: LICENSE.txt
Requires-Dist: numpy>=1.16
Dynamic: license-file
Dynamic: requires
